<?xml version="1.0" encoding="utf-8"?>
<clothingItem>
	<m_MaleModel>media\models_X\Skinned\Clothes\LeatherGauntlets.FBX</m_MaleModel>
	<m_FemaleModel>media\models_X\Skinned\Clothes\LeatherGauntlets.FBX</m_FemaleModel>
	<m_GUID>cd455823-f34c-42f9-b08a-87896d6d0ae3</m_GUID>
	<m_Static>false</m_Static>
	<m_AllowRandomHue>false</m_AllowRandomHue>
	<m_AllowRandomTint>false</m_AllowRandomTint>
	<m_AttachBone></m_AttachBone>
	<textureChoices>Clothes\Items\LeatherGauntlets</textureChoices>
</clothingItem>